pyldapi/__init__.py
pyldapi/data.py
pyldapi/exceptions.py
pyldapi/helpers.py
pyldapi/profile.py
pyldapi/renderer.py
pyldapi/renderer_container.py
pyldapi/templates/alt.html
pyldapi/templates/mem.html
pyldapi/templates/page.html
tests/__init__.py
tests/alt_template.py
tests/example.py
tests/renderer_container.py
tests/test_conneg_by_p.py
tests/test_renderer.py
pyldapi-4.2.dist-info/LICENSE
pyldapi-4.2.dist-info/METADATA
pyldapi-4.2.dist-info/WHEEL
pyldapi-4.2.dist-info/top_level.txt
pyldapi-4.2.dist-info/RECORD
