Metadata-Version: 2.1
Name: pyldapi
Version: 4.2
Summary: A very small module to add Linked Data API functionality to a Python FastAPI or Flask (v3.x) installation
Home-page: https://github.com/RDFLib/pyLDAPI
Author: Nicholas Car
Author-email: nicholas.car@surroundaustralia.com
License: LICENSE.txt
Download-URL: https://github.com/RDFLib/pyLDAPI/archive/v4.2.tar.gz
Project-URL: Bug Reports, https://github.com/RDFLib/pyLDAPI/issues
Project-URL: Source, https://github.com/RDFLib/pyLDAPI/
Keywords: Linked Data,Semantic Web,FastAPI,Python,API,RDF
Platform: UNKNOWN
Classifier: Development Status :: 4 - Beta
Classifier: Topic :: Utilities
Classifier: License :: OSI Approved :: GNU General Public License v3 or later (GPLv3+)
Classifier: Intended Audience :: Developers
Classifier: Natural Language :: English
Classifier: Programming Language :: Python :: 3
Classifier: Programming Language :: Python :: 3 :: Only
Classifier: Programming Language :: Python :: 3.4
Classifier: Programming Language :: Python :: 3.5
Classifier: Programming Language :: Python :: 3.6
Classifier: Programming Language :: Python :: 3.7
Classifier: Programming Language :: Python :: Implementation :: CPython
Classifier: Programming Language :: Python :: Implementation :: PyPy
Classifier: Topic :: Software Development :: Libraries :: Python Modules
Requires-Dist: fastapi
Requires-Dist: rdflib (>=6.0.0)
Requires-Dist: connegp
